nalaf/__init__.py
nalaf/data/__init__.py
nalaf/data/default_config.ini
nalaf/domain/__init__.py
nalaf/domain/bio/__init__.py
nalaf/domain/bio/gnormplus.py
nalaf/download_data.py
nalaf/features/__init__.py
nalaf/features/conjunction.py
nalaf/features/dictionaries.py
nalaf/features/embeddings.py
nalaf/features/parsing.py
nalaf/features/relations/__init__.py
nalaf/features/relations/context.py
nalaf/features/relations/entityhead.py
nalaf/features/relations/new/__init__.py
nalaf/features/relations/new/dependency.py
nalaf/features/relations/new/sentence.py
nalaf/features/relations/path.py
nalaf/features/relations/sentence.py
nalaf/features/simple.py
nalaf/features/stemming.py
nalaf/features/util.py
nalaf/features/window.py
nalaf/learning/__init__.py
nalaf/learning/crfsuite.py
nalaf/learning/evaluators.py
nalaf/learning/lib/__init__.py
nalaf/learning/lib/sklsvm.py
nalaf/learning/svmlight.py
nalaf/learning/taggers.py
nalaf/preprocessing/__init__.py
nalaf/preprocessing/edges.py
nalaf/preprocessing/labelers.py
nalaf/preprocessing/parsers.py
nalaf/preprocessing/spliters.py
nalaf/preprocessing/tokenizers.py
nalaf/structures/__init__.py
nalaf/structures/data.py
nalaf/structures/dataset_pipelines.py
nalaf/structures/relation_pipelines.py
nalaf/utils/__init__.py
nalaf/utils/annotation_readers.py
nalaf/utils/cache.py
nalaf/utils/db_validation.py
nalaf/utils/download.py
nalaf/utils/graph.py
nalaf/utils/graphs.py
nalaf/utils/hdfs.py
nalaf/utils/helpers.py
nalaf/utils/ncbi_utils.py
nalaf/utils/qmath.py
nalaf/utils/readers.py
nalaf/utils/tagger.py
nalaf/utils/uniprot_utils.py
nalaf/utils/writers.py
nalaf-0.6.0.dist-info/LICENSE.txt
nalaf-0.6.0.dist-info/WHEEL
nalaf-0.6.0.dist-info/METADATA
nalaf-0.6.0.dist-info/RECORD
