Metadata-Version: 2.1
Name: nalaf
Version: 0.6.0
Summary: Natural Language Framework, for NER and RE
Home-page: https://github.com/Rostlab/nalaf
License: Apache License
Keywords: NLP,NLU,NER,RE,natural language,CRF,SVM,entity extraction,relation extraction
Author: Juan Miguel Cejuela
Author-email: juanmi@tagtog.net
Requires-Python: >=3.6,<4.0
Classifier: License :: Other/Proprietary License
Classifier: Natural Language :: English
Classifier: Programming Language :: Python :: 3
Classifier: Programming Language :: Python :: 3.6
Classifier: Programming Language :: Python :: 3.7
Classifier: Programming Language :: Python :: 3.8
Classifier: Programming Language :: Python :: 3.9
Classifier: Topic :: Text Processing :: Linguistic
Requires-Dist: beautifulsoup4 (>=4.5,<5.0)
Requires-Dist: gensim (>=0.13.3,<=0.13.4.1)
Requires-Dist: hdfs (>=2.5.0,<2.6.0)
Requires-Dist: nltk (>=3.0.0,<4.0.0)
Requires-Dist: numpy (>=1.16.0,<1.17.0)
Requires-Dist: progress (>=1.2,<2.0)
Requires-Dist: python-crfsuite (>=0.9.3,<0.10.0)
Requires-Dist: requests (>=2.21,<3.0)
Requires-Dist: scikit-learn (>=0.18.1,<=0.20.3)
Requires-Dist: scipy (>=0.18.1,<1.3)
Requires-Dist: spacy (==1.2.0)
Requires-Dist: urllib3 (>=1.20,<1.25)
